MANIFEST.in
README.rst
setup.py
solr_recipe/__init__.py
solr_recipe/install.py
solr_recipe.egg-info/PKG-INFO
solr_recipe.egg-info/SOURCES.txt
solr_recipe.egg-info/dependency_links.txt
solr_recipe.egg-info/entry_points.txt
solr_recipe.egg-info/not-zip-safe
solr_recipe.egg-info/requires.txt
solr_recipe.egg-info/top_level.txt
solr_recipe/files/example-solr3.6-config/solr.xml
solr_recipe/files/example-solr3.6-config/conf/mapping-FoldToASCII.txt
solr_recipe/files/example-solr3.6-config/conf/mapping-ISOLatin1Accent.txt
solr_recipe/files/example-solr3.6-config/conf/protwords.txt
solr_recipe/files/example-solr3.6-config/conf/solrconfig.xml
solr_recipe/files/example-solr3.6-config/conf/spellings.txt
solr_recipe/files/example-solr3.6-config/conf/stopwords.txt
solr_recipe/files/example-solr3.6-config/conf/synonyms.txt