Metadata-Version: 1.0
Name: solr-recipe
Version: 1.0
Summary: Buildout recipe that installs and configures Apache Solr. The default setup works with haystack 1.2.3.
Home-page: http://github.com/espenak/solr_recipe
Author: Espen Angell Kristiansen
Author-email: post@espenak.net
License: Apache
Platform: UNKNOWN
Classifier: Development Status :: 5 - Production/Stable
Classifier: Intended Audience :: Developers
Classifier: License :: OSI Approved :: Apache Software License
Classifier: Operating System :: OS Independent
Classifier: Framework :: Buildout
Classifier: Programming Language :: Python
